ding/__init__.py
ding/compatibility.py
ding/bonus/__init__.py
ding/bonus/a2c.py
ding/bonus/c51.py
ding/bonus/common.py
ding/bonus/config.py
ding/bonus/ddpg.py
ding/bonus/dqn.py
ding/bonus/model.py
ding/bonus/pg.py
ding/bonus/ppo_offpolicy.py
ding/bonus/ppof.py
ding/bonus/sac.py
ding/bonus/sql.py
ding/bonus/td3.py
ding/config/__init__.py
ding/config/config.py
ding/config/utils.py
ding/config/example/__init__.py
ding/config/example/A2C/__init__.py
ding/config/example/A2C/gym_bipedalwalker_v3.py
ding/config/example/A2C/gym_lunarlander_v2.py
ding/config/example/C51/__init__.py
ding/config/example/C51/gym_lunarlander_v2.py
ding/config/example/C51/gym_pongnoframeskip_v4.py
ding/config/example/C51/gym_qbertnoframeskip_v4.py
ding/config/example/C51/gym_spaceInvadersnoframeskip_v4.py
ding/config/example/DDPG/__init__.py
ding/config/example/DDPG/gym_bipedalwalker_v3.py
ding/config/example/DDPG/gym_halfcheetah_v3.py
ding/config/example/DDPG/gym_hopper_v3.py
ding/config/example/DDPG/gym_lunarlandercontinuous_v2.py
ding/config/example/DDPG/gym_pendulum_v1.py
ding/config/example/DDPG/gym_walker2d_v3.py
ding/config/example/DQN/__init__.py
ding/config/example/DQN/gym_lunarlander_v2.py
ding/config/example/DQN/gym_pongnoframeskip_v4.py
ding/config/example/DQN/gym_qbertnoframeskip_v4.py
ding/config/example/DQN/gym_spaceInvadersnoframeskip_v4.py
ding/config/example/PG/__init__.py
ding/config/example/PG/gym_pendulum_v1.py
ding/config/example/PPOF/__init__.py
ding/config/example/PPOF/gym_lunarlander_v2.py
ding/config/example/PPOF/gym_lunarlandercontinuous_v2.py
ding/config/example/PPOOffPolicy/__init__.py
ding/config/example/PPOOffPolicy/gym_lunarlander_v2.py
ding/config/example/PPOOffPolicy/gym_pongnoframeskip_v4.py
ding/config/example/PPOOffPolicy/gym_qbertnoframeskip_v4.py
ding/config/example/PPOOffPolicy/gym_spaceInvadersnoframeskip_v4.py
ding/config/example/SAC/__init__.py
ding/config/example/SAC/gym_bipedalwalker_v3.py
ding/config/example/SAC/gym_halfcheetah_v3.py
DI_engine-0.5.3.dist-info/LICENSE
DI_engine-0.5.3.dist-info/METADATA
DI_engine-0.5.3.dist-info/WHEEL
DI_engine-0.5.3.dist-info/entry_points.txt
DI_engine-0.5.3.dist-info/top_level.txt
DI_engine-0.5.3.dist-info/RECORD
