Metadata-Version: 2.1
Name: DI-engine
Version: 0.5.3
Summary: Decision AI Engine
Home-page: https://github.com/opendilab/DI-engine
Author: OpenDILab Contributors
Author-email: opendilab@pjlab.org.cn
License: Apache License, Version 2.0
Keywords: Decision AI Engine
Classifier: Development Status :: 5 - Production/Stable
Classifier: Intended Audience :: Science/Research
Classifier: License :: OSI Approved :: Apache Software License
Classifier: Operating System :: POSIX :: Linux
Classifier: Operating System :: Microsoft :: Windows
Classifier: Operating System :: MacOS :: MacOS X
Classifier: Programming Language :: Python :: 3.7
Classifier: Programming Language :: Python :: 3.8
Classifier: Programming Language :: Python :: 3.9
Classifier: Programming Language :: Python :: 3.10
Classifier: Topic :: Scientific/Engineering :: Artificial Intelligence
Requires-Python: >=3.7
License-File: LICENSE
Requires-Dist: setuptools <=66.1.1
Requires-Dist: yapf ==0.29.0
Requires-Dist: gym ==0.25.1
Requires-Dist: gymnasium
Requires-Dist: torch >=1.1.0
Requires-Dist: numpy <2,>=1.18.0
Requires-Dist: DI-treetensor >=0.4.0
Requires-Dist: DI-toolkit >=0.1.0
Requires-Dist: trueskill
Requires-Dist: tensorboardX >=2.2
Requires-Dist: wandb <=0.19.0
Requires-Dist: matplotlib
Requires-Dist: easydict >=1.9
Requires-Dist: pyyaml
Requires-Dist: enum-tools
Requires-Dist: cloudpickle
Requires-Dist: hickle
Requires-Dist: tabulate
Requires-Dist: click >=7.0.0
Requires-Dist: flask <=2.0.3
Requires-Dist: werkzeug <=2.0.3
Requires-Dist: requests
Requires-Dist: responses
Requires-Dist: URLObject
Requires-Dist: pynng
Requires-Dist: sniffio
Requires-Dist: redis
Requires-Dist: mpire >=2.3.5
Requires-Dist: einops
Provides-Extra: bsuite_env
Requires-Dist: bsuite ; extra == 'bsuite_env'
Provides-Extra: common_env
Requires-Dist: ale-py ; extra == 'common_env'
Requires-Dist: autorom ; extra == 'common_env'
Requires-Dist: gym[all] ==0.25.1 ; extra == 'common_env'
Requires-Dist: cmake >=3.18.4 ; extra == 'common_env'
Requires-Dist: opencv-python ; extra == 'common_env'
Provides-Extra: dist
Requires-Dist: redis-py-cluster ==2.1.0 ; extra == 'dist'
Provides-Extra: envpool
Requires-Dist: envpool ; extra == 'envpool'
Provides-Extra: fast
Requires-Dist: numpy-stl ; extra == 'fast'
Requires-Dist: numba >=0.53.0 ; extra == 'fast'
Provides-Extra: gfootball_env
Requires-Dist: gfootball ; extra == 'gfootball_env'
Requires-Dist: kaggle-environments ; extra == 'gfootball_env'
Provides-Extra: k8s
Requires-Dist: kubernetes ; extra == 'k8s'
Provides-Extra: mario
Requires-Dist: gym-super-mario-bros >=7.3.0 ; extra == 'mario'
Provides-Extra: minigrid_env
Requires-Dist: minigrid >=2.0.0 ; extra == 'minigrid_env'
Provides-Extra: procgen_env
Requires-Dist: procgen ; extra == 'procgen_env'
Provides-Extra: slimevolleygym_env
Requires-Dist: slimevolleygym ; extra == 'slimevolleygym_env'
Provides-Extra: smac_env
Requires-Dist: pysc2 ; extra == 'smac_env'
Provides-Extra: sokoban
Requires-Dist: gym-sokoban ; extra == 'sokoban'
Provides-Extra: style
Requires-Dist: yapf ==0.29.0 ; extra == 'style'
Requires-Dist: flake8 <=3.9.2 ; extra == 'style'
Requires-Dist: importlib-metadata <5.0.0 ; extra == 'style'
Provides-Extra: test
Requires-Dist: coverage <=7.0.1,>=5 ; extra == 'test'
Requires-Dist: mock >=4.0.3 ; extra == 'test'
Requires-Dist: pytest ~=7.0.1 ; extra == 'test'
Requires-Dist: pytest-cov ~=3.0.0 ; extra == 'test'
Requires-Dist: pytest-mock ~=3.6.1 ; extra == 'test'
Requires-Dist: pytest-xdist >=1.34.0 ; extra == 'test'
Requires-Dist: pytest-rerunfailures ~=10.2 ; extra == 'test'
Requires-Dist: pytest-timeout ~=2.0.2 ; extra == 'test'
Requires-Dist: readerwriterlock ; extra == 'test'
Requires-Dist: pandas ; extra == 'test'
Requires-Dist: lz4 ; extra == 'test'
Requires-Dist: h5py ; extra == 'test'
Requires-Dist: scipy ; extra == 'test'
Requires-Dist: scikit-learn ; extra == 'test'
Requires-Dist: pettingzoo <=1.22.3 ; extra == 'test'
Requires-Dist: pygame ; extra == 'test'
Requires-Dist: opencv-python ; extra == 'test'
Requires-Dist: pyecharts ; extra == 'test'
Provides-Extra: video
Requires-Dist: moviepy ; extra == 'video'
Requires-Dist: imageio[ffmpeg] ; extra == 'video'
